Workbook

Sheet Dashboard
A2: ◼ PIXEL PATCHER — 2026 BUSINESS DASHBOARD
B5: 💰 TOTAL INCOME | D5: 📉 TOTAL EXPENSES | F5: 📈 NET PROFIT | H5: 🔧 JOBS COMPLETED
B6: =SUMIF(Income!B:B,"<>Owner Contribution",Income!E:E) | D6: =SUM(Expenses!E:E) | F6: =SUMIF(Income!B:B,"<>Owner Contribution",Income!E:E)-SUM(Expenses!E:E) | H6: =COUNTA(Income!A2:A1000)-COUNTIF(Income!B2:B1000,"Owner Contribution")
B7: Year to Date | D7: Year to Date | F7: Year to Date | H7: Year to Date
B9: 📊 AVG JOB VALUE | D9: 🚗 MILES DRIVEN | F9: 💸 MILEAGE DEDUCTION | H9: 💼 TAX RESERVE (25%)
B10: =IFERROR((SUMIF(Income!B:B,"<>Owner Contribution",Income!E:E))/(COUNTA(Income!A2:A1000)-COUNTIF(Income!B2:B1000,"Owner Contribution")),0) | D10: =SUM(Mileage!E3:E1000) | F10: =SUM(Mileage!F3:F1000) | H10: =MAX(0,(SUMIF(Income!B:B,"<>Owner Contribution",Income!E:E)-SUM(Expenses!E:E))*0.25)
B11: Per Completed Job | D11: Total YTD | F11: IRS $0.70/mile | H11: Set This Aside
A13: 📅 MONTHLY BREAKDOWN
B14: Month | D14: Income | F14: Expenses | H14: Net
B15: Jan | D15: =SUMIFS(Income!E:E,Income!A:A,">="&DATE(2026,1,1),Income!A:A,"<"&DATE(2026,2,1),Income!B:B,"<>Owner Contribution") | F15: =SUMIFS(Expenses!E:E,Expenses!A:A,">="&DATE(2026,1,1),Expenses!A:A,"<"&DATE(2026,2,1)) | H15: =D15-F15
B16: Feb | D16: =SUMIFS(Income!E:E,Income!A:A,">="&DATE(2026,2,1),Income!A:A,"<"&DATE(2026,3,1),Income!B:B,"<>Owner Contribution") | F16: =SUMIFS(Expenses!E:E,Expenses!A:A,">="&DATE(2026,2,1),Expenses!A:A,"<"&DATE(2026,3,1)) | H16: =D16-F16
B17: Mar | D17: =SUMIFS(Income!E:E,Income!A:A,">="&DATE(2026,3,1),Income!A:A,"<"&DATE(2026,4,1),Income!B:B,"<>Owner Contribution") | F17: =SUMIFS(Expenses!E:E,Expenses!A:A,">="&DATE(2026,3,1),Expenses!A:A,"<"&DATE(2026,4,1)) | H17: =D17-F17
B18: Apr | D18: =SUMIFS(Income!E:E,Income!A:A,">="&DATE(2026,4,1),Income!A:A,"<"&DATE(2026,5,1),Income!B:B,"<>Owner Contribution") | F18: =SUMIFS(Expenses!E:E,Expenses!A:A,">="&DATE(2026,4,1),Expenses!A:A,"<"&DATE(2026,5,1)) | H18: =D18-F18
B19: May | D19: =SUMIFS(Income!E:E,Income!A:A,">="&DATE(2026,5,1),Income!A:A,"<"&DATE(2026,6,1),Income!B:B,"<>Owner Contribution") | F19: =SUMIFS(Expenses!E:E,Expenses!A:A,">="&DATE(2026,5,1),Expenses!A:A,"<"&DATE(2026,6,1)) | H19: =D19-F19
B20: Jun | D20: =SUMIFS(Income!E:E,Income!A:A,">="&DATE(2026,6,1),Income!A:A,"<"&DATE(2026,7,1),Income!B:B,"<>Owner Contribution") | F20: =SUMIFS(Expenses!E:E,Expenses!A:A,">="&DATE(2026,6,1),Expenses!A:A,"<"&DATE(2026,7,1)) | H20: =D20-F20
B21: Jul | D21: =SUMIFS(Income!E:E,Income!A:A,">="&DATE(2026,7,1),Income!A:A,"<"&DATE(2026,8,1),Income!B:B,"<>Owner Contribution") | F21: =SUMIFS(Expenses!E:E,Expenses!A:A,">="&DATE(2026,7,1),Expenses!A:A,"<"&DATE(2026,8,1)) | H21: =D21-F21
B22: Aug | D22: =SUMIFS(Income!E:E,Income!A:A,">="&DATE(2026,8,1),Income!A:A,"<"&DATE(2026,9,1),Income!B:B,"<>Owner Contribution") | F22: =SUMIFS(Expenses!E:E,Expenses!A:A,">="&DATE(2026,8,1),Expenses!A:A,"<"&DATE(2026,9,1)) | H22: =D22-F22
B23: Sep | D23: =SUMIFS(Income!E:E,Income!A:A,">="&DATE(2026,9,1),Income!A:A,"<"&DATE(2026,10,1),Income!B:B,"<>Owner Contribution") | F23: =SUMIFS(Expenses!E:E,Expenses!A:A,">="&DATE(2026,9,1),Expenses!A:A,"<"&DATE(2026,10,1)) | H23: =D23-F23
B24: Oct | D24: =SUMIFS(Income!E:E,Income!A:A,">="&DATE(2026,10,1),Income!A:A,"<"&DATE(2026,11,1),Income!B:B,"<>Owner Contribution") | F24: =SUMIFS(Expenses!E:E,Expenses!A:A,">="&DATE(2026,10,1),Expenses!A:A,"<"&DATE(2026,11,1)) | H24: =D24-F24
B25: Nov | D25: =SUMIFS(Income!E:E,Income!A:A,">="&DATE(2026,11,1),Income!A:A,"<"&DATE(2026,12,1),Income!B:B,"<>Owner Contribution") | F25: =SUMIFS(Expenses!E:E,Expenses!A:A,">="&DATE(2026,11,1),Expenses!A:A,"<"&DATE(2026,12,1)) | H25: =D25-F25
B26: Dec | D26: =SUMIFS(Income!E:E,Income!A:A,">="&DATE(2026,12,1),Income!A:A,"<"&DATE(2027,1,1),Income!B:B,"<>Owner Contribution") | F26: =SUMIFS(Expenses!E:E,Expenses!A:A,">="&DATE(2026,12,1),Expenses!A:A,"<"&DATE(2027,1,1)) | H26: =D26-F26
B27: TOTAL | D27: =SUM(D15:D26) | F27: =SUM(F15:F26) | H27: =D27-F27
A29: 📆 QUARTERLY SUMMARY
B30: Quarter | D30: Income | F30: Expenses | H30: Net
B31: Q1 (Jan–Mar) | D31: =SUM(D15:D17) | F31: =SUM(F15:F17) | H31: =D31-F31
B32: Q2 (Apr–Jun) | D32: =SUM(D18:D20) | F32: =SUM(F18:F20) | H32: =D32-F32
B33: Q3 (Jul–Sep) | D33: =SUM(D21:D23) | F33: =SUM(F21:F23) | H33: =D33-F33
B34: Q4 (Oct–Dec) | D34: =SUM(D24:D26) | F34: =SUM(F24:F26) | H34: =D34-F34
A36: 📂 EXPENSES BY CATEGORY
B37: Category | D37: Amount
B38: Insurance | D38: =SUMIF(Expenses!B:B,"Insurance",Expenses!E:E)
B39: Licenses & Permits | D39: =SUMIF(Expenses!B:B,"Licenses & Permits",Expenses!E:E)
B40: Marketing | D40: =SUMIF(Expenses!B:B,"Marketing",Expenses!E:E)
B41: Tools & Equipment | D41: =SUMIF(Expenses!B:B,"Tools & Equipment",Expenses!E:E)
B42: Software | D42: =SUMIF(Expenses!B:B,"Software",Expenses!E:E)
B43: Vehicle/Mileage | D43: =SUMIF(Expenses!B:B,"Vehicle/Mileage",Expenses!E:E)
B44: Parts (resale) | D44: =SUMIF(Expenses!B:B,"Parts (resale)",Expenses!E:E)
B45: Misc | D45: =SUMIF(Expenses!B:B,"Misc",Expenses!E:E)
B47: Owner Contributions | D47: =SUMIF(Income!B:B,"Owner Contribution",Income!E:E)

Sheet Income
A1: 💰 INCOME LOG
A2: Date | B2: Type | C2: Category | D2: Description | E2: Amount | F2: Payment Method | G2: Notes
A3: 2026-02-26 | B3: Owner Contribution | C3: Capital | D3: Initial business funding | E3: 200 | F3: Transfer | G3: Seed money from personal funds
A4: ← Add rows below

Sheet Expenses
A1: 📉 EXPENSES LOG
A2: Date | B2: Category | C2: Description | D2: Vendor | E2: Amount | F2: Payment Method | G2: Notes
A3: 2026-02-26 | B3: Licenses & Permits | C3: City of Roanoke business license | D3: City of Roanoke | E3: 50 | F3: Check | G3: Annual renewal due March 1
A4: 2026-02-26 | B4: Marketing | C4: Flyer print run (15 flyers) | D4: FedEx Office | E4: 0 | F4: Card | G4: Update with actual amount
A5: 2026-02-26 | B5: Tools & Equipment | C5: Harbor Freight tool tote + supplies | D5: Harbor Freight | E5: 0 | F5: Card | G5: Update with actual amount
A6: 2026-02-26 | B6: Insurance | C6: General Liability Insurance - Feb (first month) | D6: Next Insurance | E6: 31.25 | F6: Card | G6: Monthly recurring ~$31.25/mo

Sheet Mileage
A1: 🚗 MILEAGE TRACKER
A2: IRS Rate (2026): | B2: 0.7 | C2: ← Update here if IRS rate changes
A3: Date | B3: From | C3: To | D3: Purpose | E3: Miles | F3: Deduction ($) | G3: Notes
A4: EXAMPLE | B4: Home | C4: Client address | D4: Service call | E4: 8.2 | F4: =E4*$B$2 | G4: Delete this row

Sheet Job Log
A1: 🔧 JOB LOG
A2: # | B2: Date | C2: Customer | D2: Phone | E2: Issue | F2: Service Performed | G2: Parts Used | H2: Labor ($) | I2: Parts ($) | J2: Status | K2: Total ($) | L2: Paid?
A3: Status options: Pending | In Progress | Complete | Awaiting Parts | Closed

Sheet Client Roster
A1: 👥 CLIENT ROSTER
A2: Name | B2: Phone | C2: Email | D2: Address | E2: Device(s) | F2: First Job | G2: Last Job | H2: Notes
A3: Add new clients here. Update Last Job date after each service.

Sheet Parts Tracker
A1: 🔩 PARTS TRACKER
A2: Date | B2: Part Name | C2: Supplier | D2: Cost ($) | E2: Sell Price ($) | F2: Margin ($) | G2: Margin % | H2: Job # | I2: Notes
A3: Margin ($) = Sell Price - Cost. Margin % = Margin/Cost. Formulas auto-fill: =E4-D4 and =F4/D4
A4: EXAMPLE | B4: 500GB SSD Samsung 870 | C4: Amazon | D4: 45 | E4: 54 | F4: =E4-D4 | G4: =IFERROR(F4/D4,0) | H4: 1 | I4: Delete this row

Sheet Invoice
A2: PIXEL PATCHER | E2: INVOICE
A3: FROM PIXELS TO PROCESSORS | E3: pixelpatcher.com | 540-300-2577
A6: Invoice #: | E6: BILL TO
A7: Date: | E7: Name:
A8: Due: | E8: Phone:
E9: Address:
E10: Email:
A13: # | B13: Description | F13: Qty | G13: Rate | H13: Amount
A14: 1 | H14: =IFERROR(G14*F14,0)
A15: 2 | H15: =IFERROR(G15*F15,0)
A16: 3 | H16: =IFERROR(G16*F16,0)
A17: 4 | H17: =IFERROR(G17*F17,0)
A18: 5 | H18: =IFERROR(G18*F18,0)
A19: 6 | H19: =IFERROR(G19*F19,0)
A20: 7 | H20: =IFERROR(G20*F20,0)
G23: Subtotal: | H23: =SUM(H14:H20)
G24: Parts/Other:
G25: TOTAL DUE: | H25: =H23+H24
A28: Payment due upon completion. Accepted: Cash, Venmo, CashApp, Square. 30-day labor warranty. Thank you for choosing Pixel Patcher!
